qcog_python_client/__init__.py
qcog_python_client/__version__.py
qcog_python_client/log.py
qcog_python_client/monitor/__init__.py
qcog_python_client/monitor/_wandb.py
qcog_python_client/monitor/interface.py
qcog_python_client/qcog/__init__.py
qcog_python_client/qcog/_base64utils.py
qcog_python_client/qcog/_baseclient.py
qcog_python_client/qcog/_data_uploader.py
qcog_python_client/qcog/_httpclient.py
qcog_python_client/qcog/_interfaces.py
qcog_python_client/qcog/_jsonable_parameters.py
qcog_python_client/qcog/_status.py
qcog_python_client/qcog/_version.py
qcog_python_client/qcog/qcogasync.py
qcog_python_client/qcog/qcogsync.py
qcog_python_client/qcog/pytorch/__init__.py
qcog_python_client/qcog/pytorch/agent.py
qcog_python_client/qcog/pytorch/handler.py
qcog_python_client/qcog/pytorch/types.py
qcog_python_client/qcog/pytorch/utils.py
qcog_python_client/qcog/pytorch/discover/__init__.py
qcog_python_client/qcog/pytorch/discover/discoverhandler.py
qcog_python_client/qcog/pytorch/discover/types.py
qcog_python_client/qcog/pytorch/discover/utils.py
qcog_python_client/qcog/pytorch/parameters/__init__.py
qcog_python_client/qcog/pytorch/parameters/paramshandler.py
qcog_python_client/qcog/pytorch/train/__init__.py
qcog_python_client/qcog/pytorch/train/trainhandler.py
qcog_python_client/qcog/pytorch/upload/__init__.py
qcog_python_client/qcog/pytorch/upload/uploadhandler.py
qcog_python_client/qcog/pytorch/upload/utils.py
qcog_python_client/qcog/pytorch/validate/__init__.py
qcog_python_client/qcog/pytorch/validate/_setup_monitor_import.py
qcog_python_client/qcog/pytorch/validate/_validate_model_module.py
qcog_python_client/qcog/pytorch/validate/utils.py
qcog_python_client/qcog/pytorch/validate/validatehandler.py
qcog_python_client/schema/__init__.py
qcog_python_client/schema/common.py
qcog_python_client/schema/generated_schema/models.py
qcog_python_client-0.4.5.dist-info/licenses/LICENSE
qcog_python_client-0.4.5.dist-info/METADATA
qcog_python_client-0.4.5.dist-info/WHEEL
qcog_python_client-0.4.5.dist-info/top_level.txt
qcog_python_client-0.4.5.dist-info/RECORD
