Metadata-Version: 2.4
Name: qcog_python_client
Version: 0.4.5
Summary: qcog python client
License-File: LICENSE
Requires-Dist: requests
Requires-Dist: pandas
Requires-Dist: numpy
Requires-Dist: aiohttp
Requires-Dist: pydantic
Requires-Dist: typing_extensions
Requires-Dist: pydantic-settings
Requires-Dist: anyio
Requires-Dist: wandb>=0.17.7
Provides-Extra: dev
Requires-Dist: build; extra == "dev"
Requires-Dist: mypy; extra == "dev"
Requires-Dist: ruff; extra == "dev"
Requires-Dist: pytest; extra == "dev"
Requires-Dist: pandas-stubs; extra == "dev"
Requires-Dist: types-requests; extra == "dev"
Requires-Dist: setuptools_scm[toml]>=8; extra == "dev"
Requires-Dist: sphinx; extra == "dev"
Requires-Dist: sphinx_rtd_theme; extra == "dev"
Requires-Dist: pydantic-settings; extra == "dev"
Requires-Dist: datamodel-code-generator; extra == "dev"
Requires-Dist: pytest-asyncio; extra == "dev"
Provides-Extra: examples
Requires-Dist: scikit-learn; extra == "examples"
Requires-Dist: torch; extra == "examples"
Requires-Dist: pillow; extra == "examples"
Dynamic: license-file
